Workbook

Sheet Summary
A1: Task 3.3 - Prompt Engineering Portfolio: Evaluation Sheet
A2: Skill Set Go EduTech - AI/ML Internship, Week 3 | Offer ID: SSG/AIML/B1/0291 | 4 task types x 3 prompt versions = 12 evaluated runs
A4: Score by task type and prompt version (share of checks passed; see 'Evaluation Log' and 'Rubrics')
A5: Task type | B5: v1 (baseline) | C5: v2 | D5: v3 | E5: Change v1 to v3
A6: Reasoning | B6: ='Evaluation Log'!P2 -> 0.66666667 | C6: ='Evaluation Log'!P3 -> 0.66666667 | D6: ='Evaluation Log'!P4 -> 1 | E6: =D6-B6 -> 0.33333333
A7: Extraction | B7: ='Evaluation Log'!P5 -> 0 | C7: ='Evaluation Log'!P6 -> 0.83333333 | D7: ='Evaluation Log'!P7 -> 1 | E7: =D7-B7 -> 1
A8: Summarization | B8: ='Evaluation Log'!P8 -> 0.71428571 | C8: ='Evaluation Log'!P9 -> 0.85714286 | D8: ='Evaluation Log'!P10 -> 1 | E8: =D8-B8 -> 0.28571429
A9: Coding | B9: ='Evaluation Log'!P11 -> 0.16666667 | C9: ='Evaluation Log'!P12 -> 0.5 | D9: ='Evaluation Log'!P13 -> 1 | E9: =D9-B9 -> 0.83333333
A10: Average | B10: =AVERAGE(B6:B9) -> 0.38690476 | C10: =AVERAGE(C6:C9) -> 0.71428571 | D10: =AVERAGE(D6:D9) -> 1 | E10: =D10-B10 -> 0.61309524
A29: Key findings
A30: 1. Explicit, checkable constraints drove the gains. Coding went from 17% to 50% to 100% and Extraction from 0% to 83% to 100% as format, error behaviour and output rules were spelled out.
A31: 2. Reasoning: all three versions reached the correct answer ($51). Iterating changed the format and made the work checkable (every purchase option listed, fixed final line), not the correctness. This problem was too easy to show an accuracy benefit from 'think step by step'; a harder problem would be needed.
A32: 3. Summarization: 'two sentences' did not control length (55 words). A word cap plus a required-content list produced a 36-word summary that contains all four required points and nothing extra.
A33: 4. Coding: the baseline function silently returned 0 for '', 'abc' and '1x', and 300 for '-5m', and failed on upper-case input. Naming the error contract in the prompt fixed all of that; asking for type hints, a docstring and tests added the documentation checks (the 11 generated pytest cases pass).
A34: 5. Constraints that were not stated (output format, length, error behaviour) were not reliably met until they were stated. Behaviour the model did by default (e.g. returning null for the missing phone number in E-2) needed no extra instruction.
A35: Method and limitations
A36: Each prompt was run once. The outputs in the log were produced by Claude (the AI assistant used to prepare this sheet) in response to each prompt exactly as written, then scored by script. They are NOT from a blind, independent run, and the rubrics were written alongside the prompts, so baseline (v1) results may look better than a cold run would.
A37: Scoring is automated where possible: JSON parsing, word and sentence counts, keyword presence, executing the generated function on test cases, and running the generated pytest file. One summarization check per row ('no invented facts') was done manually by reading each output against the source text.
A38: Limits: one task per category, one run per prompt (LLM output varies between runs), 3 to 7 checks each. Treat this as a demonstration of the evaluate-and-iterate method, not a benchmark.
A39: Legend: blue numbers in 'Evaluation Log' are measured check results (1 = pass, 0 = fail) typed in from the automated scoring; black cells are formulas. No cells need to be filled in.

Sheet Evaluation Log
A1: ID | B1: Category | C1: Prompt version | D1: Prompt (verbatim) | E1: What changed and why | F1: Model output (verbatim) | G1: Check 1 | H1: Check 2 | I1: Check 3 | J1: Check 4 | K1: Check 5 | L1: Check 6 | M1: Check 7 | N1: Checks passed | O1: Checks total | P1: Score | Q1: Measured notes
A2: R-1 | B2: Reasoning | C2: v1 (baseline) | D2: A bakery sells muffins at $3 each, or a box of 6 for $15. Sam wants exactly 20 muffins at the lowest total cost. How much will Sam pay? | E2: Baseline: the bare question, no instructions. | F2: Sam pays $51. A box of 6 costs $15 ($2.50 per muffin), which beats the $3 single price, so use as many boxes as fit into 20 muffins: 3 boxes = 18 muffins = $45. The remaining 2 muffins are bought singly: 2 x $3 = $6. Total: $45 + $6 = $51. | G2: 1 | H2: 1 | I2: 0 | N2: =SUM(G2:M2) -> 2 | O2: =COUNT(G2:M2) -> 3 | P2: =IF(O2=0,0,N2/O2) -> 0.66666667
A3: R-2 | B3: Reasoning | C3: v2 | D3: A bakery sells muffins at $3 each, or a box of 6 for $15. Sam wants exactly 20 muffins at the lowest total cost. How much will Sam pay? Think step by step before giving your answer. | E3: Added 'Think step by step' to encourage visible reasoning. | F3: Step 1: A box of 6 costs $15, which is $2.50 per muffin - cheaper than the $3 single price - so boxes should be used wherever possible. Step 2: 20 / 6 = 3 boxes with a remainder of 2. Three boxes give 18 muffins. Step 3: The last 2 muffins can't be another box (that would give 24, not exactly 20), so they are bought singly: 2 x $3 = $6. Step 4: Cost = 3 x $15 + $6 = $45 + $6 = $51. Sam pays $51. | G3: 1 | H3: 1 | I3: 0 | N3: =SUM(G3:M3) -> 2 | O3: =COUNT(G3:M3) -> 3 | P3: =IF(O3=0,0,N3/O3) -> 0.66666667
A4: R-3 | B4: Reasoning | C4: v3 | D4: A bakery sells muffins at $3 each, or a box of 6 for $15. Sam wants exactly 20 muffins at the lowest total cost. How much will Sam pay? Solve this by: 1. Listing every way to buy exactly 20 muffins using boxes of 6 and single muffins. 2. Calculating the total cost of each way. 3. Choosing the cheapest and checking that it totals exactly 20 muffins. End with a final line in exactly this format: ANSWER: $<amount> | E4: Replaced the generic instruction with an explicit procedure (enumerate every option, cost each, verify the count) and a fixed final-line format so the answer can be checked automatically. | F4: 1. Ways to buy exactly 20 muffins (6b + s = 20, b = boxes, s = singles): - 0 boxes + 20 singles - 1 box + 14 singles - 2 boxes + 8 singles - 3 boxes + 2 singles (4 boxes would be 24 muffins, which is more than 20.) 2. Costs: - 0 boxes: 20 x $3 = $60 - 1 box: $15 + 14 x $3 = $57 - 2 boxes: $30 + 8 x $3 = $54 - 3 boxes: $45 + 2 x $3 = $51 3. Cheapest is 3 boxes + 2 singles at $51. Check: 3 x 6 + 2 = 20 muffins. ANSWER: $51 | G4: 1 | H4: 1 | I4: 1 | N4: =SUM(G4:M4) -> 3 | O4: =COUNT(G4:M4) -> 3 | P4: =IF(O4=0,0,N4/O4) -> 1
A5: E-1 | B5: Extraction | C5: v1 (baseline) | D5: Get the important details from this email. Email: Hi team, this is Priya Nair from Brightline Logistics. Our order #48213 (placed 3 March) arrived damaged - 2 of the 12 monitors have cracked screens. We paid $3,480 in total and would like a replacement for the two units, not a refund. Please reply to priya.nair@brightline.example. Also, I'll be out of office from the 20th. | E5: Baseline: vague request, no output format. | F5: Here are the key details: - Sender: Priya Nair of Brightline Logistics - Order: #48213, placed 3 March - Problem: the order arrived damaged - 2 of the 12 monitors have cracked screens - Amount paid: $3,480 - Request: replacement of the two damaged units (not a refund) - Contact: priya.nair@brightline.example - Note: she will be out of office from the 20th | G5: 0 | H5: 0 | I5: 0 | J5: 0 | K5: 0 | L5: 0 | N5: =SUM(G5:M5) -> 0 | O5: =COUNT(G5:M5) -> 6 | P5: =IF(O5=0,0,N5/O5) -> 0 | Q5: Output is not JSON (free-form text), so no field could be machine-checked.
A6: E-2 | B6: Extraction | C6: v2 | D6: Extract these fields from the email below as JSON, using exactly these keys: customer_name, company, order_id, order_date, issue, total_paid, resolution_requested, phone. Email: Hi team, this is Priya Nair from Brightline Logistics. Our order #48213 (placed 3 March) arrived damaged - 2 of the 12 monitors have cracked screens. We paid $3,480 in total and would like a replacement for the two units, not a refund. Please reply to priya.nair@brightline.example. Also, I'll be out of office from the 20th. | E6: Asked for JSON with exactly named keys so the output has a fixed structure. | F6: ```json { "customer_name": "Priya Nair", "company": "Brightline Logistics", "order_id": "48213", "order_date": "3 March", "issue": "2 of the 12 monitors arrived with cracked screens", "total_paid": 3480, "resolution_requested": "Replacement of the two damaged units", "phone": null } ``` The email doesn't include a phone number, so I set that field to null. | G6: 0 | H6: 1 | I6: 1 | J6: 1 | K6: 1 | L6: 1 | N6: =SUM(G6:M6) -> 5 | O6: =COUNT(G6:M6) -> 6 | P6: =IF(O6=0,0,N6/O6) -> 0.83333333 | Q6: JSON only parses after stripping the code fence/commentary around it.
A7: E-3 | B7: Extraction | C7: v3 | D7: Extract information from the email below and return ONLY a JSON object (no code fences, no commentary) with exactly these keys: - customer_name (string) - company (string) - order_id (string, digits only, no '#') - order_date (string, as written in the email) - issue (string, one sentence) - total_paid (number, no currency symbol) - resolution_requested (string) - phone (string) Rules: use null for any field the email does not state; never guess or invent values; ignore details unrelated to these fields. Email: Hi team, this is Priya Nair from Brightline Logistics. Our order #48213 (placed 3 March) arrived damaged - 2 of the 12 monitors have cracked screens. We paid $3,480 in total and would like a replacement for the two units, not a refund. Please reply to priya.nair@brightline.example. Also, I'll be out of office from the 20th. | E7: Added field types, null-for-missing and no-guessing rules, 'JSON only' (no fences or commentary) and an instruction to ignore unrelated details, so the output can be parsed directly. | F7: { "customer_name": "Priya Nair", "company": "Brightline Logistics", "order_id": "48213", "order_date": "3 March", "issue": "2 of the 12 monitors arrived with cracked screens.", "total_paid": 3480, "resolution_requested": "Replacement of the two damaged units, not a refund", "phone": null } | G7: 1 | H7: 1 | I7: 1 | J7: 1 | K7: 1 | L7: 1 | N7: =SUM(G7:M7) -> 6 | O7: =COUNT(G7:M7) -> 6 | P7: =IF(O7=0,0,N7/O7) -> 1
A8: S-1 | B8: Summarization | C8: v1 (baseline) | D8: Summarize this. The city of Marlow ran a six-month bike-share pilot from April to September. The program placed 300 bikes at 40 docking stations, mostly near the university and the central train station. Riders made an average of 4,200 trips per day, and a follow-up survey of 1,100 riders found that 18% said they used the bikes in place of a car trip. Operating costs came to $410,000, about $90,000 over budget, mainly because of vandalism and the cost of redistributing bikes between stations. The council noted that the pilot ran only during the warmest months, so winter demand is unknown. A vote on whether to expand the program to 120 stations is scheduled for November. | E8: Baseline: 'Summarize this.' | F8: Marlow's six-month bike-share pilot (300 bikes, 40 stations, April to September) averaged 4,200 trips a day, and 18% of surveyed riders said they replaced a car trip with a bike. It cost $410,000, roughly $90,000 over budget because of vandalism and the expense of moving bikes between stations. Because it only ran in warm months, winter demand is unknown, and the council votes in November on expanding to 120 stations. | G8: 0 | H8: 0 | I8: 1 | J8: 1 | K8: 1 | L8: 1 | M8: 1 | N8: =SUM(G8:M8) -> 5 | O8: =COUNT(G8:M8) -> 7 | P8: =IF(O8=0,0,N8/O8) -> 0.71428571 | Q8: 70 words, 3 sentence(s).
A9: S-2 | B9: Summarization | C9: v2 | D9: Summarize this for a busy city manager in two sentences. The city of Marlow ran a six-month bike-share pilot from April to September. The program placed 300 bikes at 40 docking stations, mostly near the university and the central train station. Riders made an average of 4,200 trips per day, and a follow-up survey of 1,100 riders found that 18% said they used the bikes in place of a car trip. Operating costs came to $410,000, about $90,000 over budget, mainly because of vandalism and the cost of redistributing bikes between stations. The council noted that the pilot ran only during the warmest months, so winter demand is unknown. A vote on whether to expand the program to 120 stations is scheduled for November. | E9: Added an audience (busy city manager) and a sentence limit. | F9: Marlow's six-month bike-share pilot averaged 4,200 trips a day, with 18% of surveyed riders replacing a car trip, but it cost $410,000, about $90,000 over budget, due to vandalism and bike redistribution. Winter demand is untested because the pilot ran only in warm months, and the council votes in November on expanding to 120 stations. | G9: 0 | H9: 1 | I9: 1 | J9: 1 | K9: 1 | L9: 1 | M9: 1 | N9: =SUM(G9:M9) -> 6 | O9: =COUNT(G9:M9) -> 7 | P9: =IF(O9=0,0,N9/O9) -> 0.85714286 | Q9: 55 words, 2 sentence(s).
A10: S-3 | B10: Summarization | C10: v3 | D10: Summarize the text below for a busy city manager. Requirements: - Maximum 40 words, in 2 sentences - Must include: the usage result, the cost overrun, the winter-demand caveat, and the November vote - Use only facts stated in the text; do not add anything new Text: The city of Marlow ran a six-month bike-share pilot from April to September. The program placed 300 bikes at 40 docking stations, mostly near the university and the central train station. Riders made an average of 4,200 trips per day, and a follow-up survey of 1,100 riders found that 18% said they used the bikes in place of a car trip. Operating costs came to $410,000, about $90,000 over budget, mainly because of vandalism and the cost of redistributing bikes between stations. The council noted that the pilot ran only during the warmest months, so winter demand is unknown. A vote on whether to expand the program to 120 stations is scheduled for November. | E10: Replaced the sentence limit with a word cap plus a required-content list and an instruction to add nothing new. | F10: Marlow's bike-share pilot averaged 4,200 trips a day but ran about $90,000 over budget. Winter demand is unknown because it ran only in warm months, and the council votes in November on expanding to 120 stations. | G10: 1 | H10: 1 | I10: 1 | J10: 1 | K10: 1 | L10: 1 | M10: 1 | N10: =SUM(G10:M10) -> 7 | O10: =COUNT(G10:M10) -> 7 | P10: =IF(O10=0,0,N10/O10) -> 1 | Q10: 36 words, 2 sentence(s).
A11: C-1 | B11: Coding | C11: v1 (baseline) | D11: Write a Python function that converts a duration string like '1h30m' into seconds. | E11: Baseline: the bare task. | F11: ```python import re def parse_duration(s): total = 0 units = {"h": 3600, "m": 60, "s": 1} for value, unit in re.findall(r"(\d+)([hms])", s): total += int(value) * units[unit] return total print(parse_duration("1h30m")) # 5400 ``` This finds each number-plus-unit pair and adds up its value in seconds. | G11: 1 | H11: 0 | I11: 0 | J11: 0 | K11: 0 | L11: 0 | N11: =SUM(G11:M11) -> 1 | O11: =COUNT(G11:M11) -> 6 | P11: =IF(O11=0,0,N11/O11) -> 0.16666667 | Q11: '1H30M' -> 0 (expected 5400); '' did not raise ValueError (returned 0); 'abc' did not raise ValueError (returned 0); '1x' did not raise ValueError (returned 0); '-5m' did not raise ValueError (returned 300); '1h30' did not raise ValueError (returned 3600)
A12: C-2 | B12: Coding | C12: v2 | D12: Write a Python function that converts a duration string like '1h30m' into seconds. Requirements: support h, m and s in any combination (e.g. '1h30m', '45s', '90m', '1h 30m 15s'); allow optional spaces; be case-insensitive; raise ValueError for empty, malformed or negative input (e.g. '', 'abc', '1x', '-5m', '1h30'). | E12: Specified supported units and formats, case-insensitivity, and an error contract (ValueError for invalid input, with examples). | F12: ```python import re _TOKEN = re.compile(r"(\d+)\s*([hms])", re.IGNORECASE) _VALID = re.compile(r"\s*(?:\d+\s*[hms]\s*)+", re.IGNORECASE) def parse_duration(s): if not _VALID.fullmatch(s): raise ValueError(f"invalid duration: {s!r}") units = {"h": 3600, "m": 60, "s": 1} return sum(int(n) * units[u.lower()] for n, u in _TOKEN.findall(s)) ``` The whole string is validated first, then each number-plus-unit pair is summed. | G12: 1 | H12: 1 | I12: 1 | J12: 0 | K12: 0 | L12: 0 | N12: =SUM(G12:M12) -> 3 | O12: =COUNT(G12:M12) -> 6 | P12: =IF(O12=0,0,N12/O12) -> 0.5
A13: C-3 | B13: Coding | C13: v3 | D13: Write a Python function that converts a duration string like '1h30m' into seconds. Requirements: support h, m and s in any combination (e.g. '1h30m', '45s', '90m', '1h 30m 15s'); allow optional spaces; be case-insensitive; raise ValueError for empty, malformed or negative input (e.g. '', 'abc', '1x', '-5m', '1h30'). Also: add type hints and a docstring, and include a small set of pytest tests covering normal and invalid inputs. Return only code blocks, with no explanation. | E13: Added deliverable requirements: type hints, a docstring, pytest tests, and code only. | F13: ```python import re import pytest _TOKEN = re.compile(r"(\d+)\s*([hms])", re.IGNORECASE) _VALID = re.compile(r"\s*(?:\d+\s*[hms]\s*)+", re.IGNORECASE) _SECONDS = {"h": 3600, "m": 60, "s": 1} def parse_duration(text: str) -> int: """Convert a duration string such as '1h30m' or '1h 30m 15s' into total seconds. Supports h, m and s units in any combination, optional whitespace, and upper- or lower-case letters. Raises: ValueError: if the text is empty, malformed, or contains a negative value. """ if not _VALID.fullmatch(text): raise ValueError(f"invalid duration: {text!r}") return sum(int(n) * _SECONDS[u.lower()] for n, u in _TOKEN.findall(text)) @pytest.mark.parametrize( "text, expected", [("1h30m", 5400), ("45s", 45), ("2h", 7200), ("90m", 5400), ("1h 30m 15s", 5415), ("1H30M", 5400)], ) def test_valid(text, expected): assert parse_duration(text) == expected @pytest.mark.parametrize("text", ["", "abc", "1x", "-5m", "1h30"]) def test_invalid(text): with pytest.raises(ValueError): parse_duration(text) ``` | G13: 1 | H13: 1 | I13: 1 | J13: 1 | K13: 1 | L13: 1 | N13: =SUM(G13:M13) -> 6 | O13: =COUNT(G13:M13) -> 6 | P13: =IF(O13=0,0,N13/O13) -> 1 | Q13: pytest: 11 passed in 0.02s

Sheet Rubrics
A1: Task type | B1: Check | C1: What is checked | D1: How it is measured
A2: Reasoning | B2: 1 | C2: Final dollar amount stated is $51 (the true minimum cost) | D2: Automated: last $ amount in the output
A3: Reasoning | B3: 2 | C3: Shows the winning combination (3 boxes plus 2 single muffins) | D3: Automated: text pattern match
A4: Reasoning | B4: 3 | C4: Last line is exactly 'ANSWER: $51' | D4: Automated: exact string match
A5: Extraction | B5: 1 | C5: Entire output parses as JSON (no code fence or commentary) | D5: Automated: json.loads on the raw output
A6: Extraction | B6: 2 | C6: Has exactly the 8 requested keys, no more, no fewer | D6: Automated: key set comparison
A7: Extraction | B7: 3 | C7: total_paid is the number 3480 (not a string) | D7: Automated: value and type check
A8: Extraction | B8: 4 | C8: order_id is '48213' (no '#') | D8: Automated: exact value
A9: Extraction | B9: 5 | C9: phone is null (the email gives no phone number) | D9: Automated: value is None
A10: Extraction | B10: 6 | C10: customer_name and company are correct | D10: Automated: exact values
A11: Summarization | B11: 1 | C11: 40 words or fewer | D11: Automated: word count
A12: Summarization | B12: 2 | C12: Exactly 2 sentences | D12: Automated: sentence split
A13: Summarization | B13: 3 | C13: Includes the usage result (4,200 trips/day or 18%) | D13: Automated: keyword match
... A23: Coding | B23: 6 | C23: Ships its own tests, and they pass | D23: Automated: pytest run on the generated file

Sheet Test Inputs
A1: Test input | B1: Content
A2: Reasoning question | B2: A bakery sells muffins at $3 each, or a box of 6 for $15. Sam wants exactly 20 muffins at the lowest total cost. How much will Sam pay? Ground truth: 3 boxes (18 muffins, $45) + 2 singles ($6) = $51. Other exact-20 options cost $54, $57 or $60.
A3: Extraction email | B3: Hi team, this is Priya Nair from Brightline Logistics. Our order #48213 (placed 3 March) arrived damaged - 2 of the 12 monitors have cracked screens. We paid $3,480 in total and would like a replacement for the two units, not a refund. Please reply to priya.nair@brightline.example. Also, I'll be out of office from the 20th. Ground truth: order_id 48213; total_paid 3480; phone not stated (null); the out-of-office remark is not one of the fields.
A4: Summarization text | B4: The city of Marlow ran a six-month bike-share pilot from April to September. The program placed 300 bikes at 40 docking stations, mostly near the university and the central train station. Riders made an average of 4,200 trips per day, and a follow-up survey of 1,100 riders found that 18% said they used the bikes in place of a car trip. Operating costs came to $410,000, about $90,000 over budget, mainly because of vandalism and the cost of redistributing bikes between stations. The council noted that the pilot ran only during the warmest months, so winter demand is unknown. A vote on whether to expand the program to 120 stations is scheduled for November. (114 words. Original text written for this exercise.)
A5: Coding task | B5: Write a Python function that converts a duration string like '1h30m' into seconds. Hidden test contract: h/m/s in any combination, optional spaces, case-insensitive; ValueError for empty, malformed or negative input.
